README.md
setup.py
frida_push/__init__.py
frida_push/command.py
frida_push.egg-info/PKG-INFO
frida_push.egg-info/SOURCES.txt
frida_push.egg-info/dependency_links.txt
frida_push.egg-info/entry_points.txt
frida_push.egg-info/requires.txt
frida_push.egg-info/top_level.txt