Metadata-Version: 1.0
Name: frida-push
Version: 1.0.8
Summary: Wrapper tool to identify the remote device and push device specific frida-server binary.
Home-page: https://github.com/AndroidTamer/frida-push
Author: AndroidTamer
Author-email: github@androidtamer.com
License: GPLv3
Platform: UNKNOWN
